build/lib/build/lib/build/lib/build/lib/example/example_pyqt5.py
build/lib/build/lib/build/lib/build/lib/example/ui/__init__.py
build/lib/build/lib/build/lib/build/lib/example/ui/example_pyqt5_ui.py
build/lib/build/lib/build/lib/build/lib/qdarkgraystyle/__init__.py
build/lib/build/lib/build/lib/build/lib/qdarkgraystyle/compile_qrc.py
build/lib/build/lib/build/lib/build/lib/qdarkgraystyle/pyqt5_style_rc.py
build/lib/build/lib/build/lib/build/lib/tests/__init__.py
build/lib/build/lib/build/lib/build/lib/tests/test_example_pyqt5.py
build/lib/build/lib/build/lib/example/example_pyqt5.py
build/lib/build/lib/build/lib/example/ui/__init__.py
build/lib/build/lib/build/lib/example/ui/example_pyqt5_ui.py
build/lib/build/lib/build/lib/qdarkgraystyle/__init__.py
build/lib/build/lib/build/lib/qdarkgraystyle/compile_qrc.py
build/lib/build/lib/build/lib/qdarkgraystyle/pyqt5_style_rc.py
build/lib/build/lib/build/lib/tests/__init__.py
build/lib/build/lib/build/lib/tests/test_example_pyqt5.py
build/lib/build/lib/build/lib/tests/example/example_pyqt5.py
build/lib/build/lib/build/lib/tests/example/ui/__init__.py
build/lib/build/lib/build/lib/tests/example/ui/example_pyqt5_ui.py
build/lib/build/lib/example/example_pyqt5.py
build/lib/build/lib/example/ui/__init__.py
build/lib/build/lib/example/ui/example_pyqt5_ui.py
build/lib/build/lib/qdarkgraystyle/__init__.py
build/lib/build/lib/qdarkgraystyle/compile_qrc.py
build/lib/build/lib/qdarkgraystyle/pyqt5_style_rc.py
build/lib/build/lib/tests/__init__.py
build/lib/build/lib/tests/test_example_pyqt5.py
build/lib/build/lib/tests/example/example_pyqt5.py
build/lib/build/lib/tests/example/ui/__init__.py
build/lib/build/lib/tests/example/ui/example_pyqt5_ui.py
build/lib/example/example_pyqt5.py
build/lib/example/ui/__init__.py
build/lib/example/ui/example_pyqt5_ui.py
build/lib/qdarkgraystyle/__init__.py
build/lib/qdarkgraystyle/compile_qrc.py
build/lib/qdarkgraystyle/pyqt5_style_rc.py
build/lib/tests/__init__.py
qdarkgraystyle-2.0.0.dist-info/LICENSE
qdarkgraystyle-2.0.0.dist-info/METADATA
qdarkgraystyle-2.0.0.dist-info/WHEEL
qdarkgraystyle-2.0.0.dist-info/top_level.txt
qdarkgraystyle-2.0.0.dist-info/RECORD
