Metadata-Version: 2.1
Name: qdarkgraystyle
Version: 2.0.0
Summary: A dark gray stylesheet for PyQt/PySide applications
Author-email: Michell Stuttgart <michellstut@gmail.com>
License: The MIT License (MIT)
Project-URL: Documentation, https://github.com/mstuttgart/qdarkgraystyle/tree/main#readme
Project-URL: Source, https://github.com/mstuttgart/qdarkgraystyle
Project-URL: Tracker, https://github.com/mstuttgart/qdarkgraystyle/issues
Classifier: Development Status :: 5 - Production/Stable
Classifier: Environment :: X11 Applications :: Qt
Classifier: Environment :: Win32 (MS Windows)
Classifier: Intended Audience :: Developers
Classifier: License :: OSI Approved :: MIT License
Classifier: Operating System :: Microsoft :: Windows
Classifier: Operating System :: POSIX :: Linux
Classifier: Operating System :: MacOS
Classifier: Programming Language :: Python :: 3 :: Only
Classifier: Programming Language :: Python :: 3.8
Classifier: Programming Language :: Python :: 3.9
Classifier: Programming Language :: Python :: 3.10
Classifier: Programming Language :: Python :: 3.11
Requires-Python: >=3.8.1
License-File: LICENSE
Requires-Dist: PyQt5 >=5.6
Provides-Extra: test
Requires-Dist: black ==21.9b0 ; extra == 'test'
Requires-Dist: check-manifest ==0.49 ; extra == 'test'
Requires-Dist: pytest ; extra == 'test'
